{
  "name": "aws-designer",
  "image": "mcr.microsoft.com/devcontainers/javascript-node:1-22-bookworm",
  "forwardPorts": [5173, 8787],
  "portsAttributes": {
    "5173": {
      "label": "Vite",
      "onAutoForward": "notify"
    },
    "8787": {
      "label": "API",
      "onAutoForward": "notify"
    }
  },
  "postCreateCommand": "npm ci",
  "customizations": {
    "vscode": {
      "extensions": [
        "dbaeumer.vscode-eslint",
        "bradlc.vscode-tailwindcss",
        "connor4312.esbuild-problem-matchers"
      ]
    }
  },
  "remoteUser": "node"
}
